{
    "key": "group_5e4148a23401a",
    "title": "CPT: BlogPost",
    "fields": [
        {
            "key": "field_5e4148ac36bc3",
            "label": "Short Description",
            "name": "shortDescription",
            "type": "textarea",
            "instructions": "",
            "required": 0,
            "conditional_logic": 0,
            "wrapper": {
                "width": "",
                "class": "",
                "id": ""
            },
            "default_value": "",
            "placeholder": "",
            "maxlength": "",
            "rows": 2,
            "new_lines": ""
        },
        {
            "key": "field_5e4149a3327c6",
            "label": "Hero Image",
            "name": "heroImage",
            "type": "image",
            "instructions": "",
            "required": 1,
            "conditional_logic": 0,
            "wrapper": {
                "width": "",
                "class": "",
                "id": ""
            },
            "return_format": "array",
            "preview_size": "medium",
            "library": "all",
            "min_width": "",
            "min_height": "",
            "min_size": "",
            "max_width": 1920,
            "max_height": 700,
            "max_size": "",
            "mime_types": ""
        },
        {
            "key": "field_5e414a8109de4",
            "label": "Thumbnail",
            "name": "thumbnail",
            "type": "image",
            "instructions": "ratio  3:2",
            "required": 0,
            "conditional_logic": 0,
            "wrapper": {
                "width": "",
                "class": "",
                "id": ""
            },
            "return_format": "id",
            "preview_size": "medium",
            "library": "all",
            "min_width": "",
            "min_height": "",
            "min_size": "",
            "max_width": "",
            "max_height": "",
            "max_size": "",
            "mime_types": ""
        }
    ],
    "location": [
        [
            {
                "param": "post_type",
                "operator": "==",
                "value": "post"
            }
        ]
    ],
    "menu_order": 0,
    "position": "normal",
    "style": "default",
    "label_placement": "top",
    "instruction_placement": "label",
    "hide_on_screen": "",
    "active": 1,
    "description": "",
    "modified": 1581337255
}